clvm_tools_rs-0.4.0.dist-info/METADATA
clvm_tools_rs-0.4.0.dist-info/WHEEL
clvm_tools_rs-0.4.0.dist-info/license_files/LICENSE
clvm_tools_rs/__init__.py
clvm_tools_rs/clvm_tools_rs.abi3.so
clvm_tools_rs-0.4.0.dist-info/RECORD
