Metadata-Version: 2.4
Name: clvm_tools_rs
Version: 0.4.0
License-File: LICENSE
Summary: tools for working with chialisp language; compiler, repl, python and wasm bindings
Keywords: chia,chialisp,clvm
Author: Art Yerkes <art.yerkes@gmail.com>
Author-email: Art Yerkes <art.yerkes@gmail.com>
License: Apache-2.0
Project-URL: Source Code, https://github.com/Chia-Network/clvm_tools_rs
